defn_cdktf_provider_vault/__init__.py
defn_cdktf_provider_vault/main.py
defn_cdktf_provider_vault/_jsii/__init__.py
defn_cdktf_provider_vault/_jsii/hashicorp_vault@0.0.0.jsii.tgz
defn_cdktf_provider_vault/_jsii/main.py
defn_cdktf_provider_vault-0.4.1.dist-info/METADATA
defn_cdktf_provider_vault-0.4.1.dist-info/WHEEL
defn_cdktf_provider_vault-0.4.1.dist-info/namespace_packages.txt
defn_cdktf_provider_vault-0.4.1.dist-info/top_level.txt
defn_cdktf_provider_vault-0.4.1.dist-info/RECORD
